{
  "class": "com.runrev.engine.graphic",
  "customPropertySets": {
    "cGlx2TimeStamp": {
      "checksum": ""
    },
    "cREVGeneral": {
      "revUniqueID": "1234839342224"
    }
  },
  "properties": {
    "altId": "0",
    "angle": "0",
    "antiAliased": "false",
    "arcAngle": "360",
    "arrowSize": "3",
    "backColor": "",
    "behavior": "",
    "blendLevel": "0",
    "borderColor": "",
    "borderWidth": "2",
    "bottomColor": "",
    "cantSelect": "false",
    "capStyle": "round",
    "coloroverlay": "",
    "dashes": "",
    "disabled": "false",
    "dontResize": "false",
    "dropshadow": "",
    "editMode": "none",
    "endArrow": "false",
    "fillGradient": "",
    "fillRule": "none",
    "filled": "false",
    "focusColor": "",
    "foreColor": "64,64,64",
    "hiliteColor": "",
    "id": "1078",
    "ink": "srcCopy",
    "innerglow": "",
    "innershadow": "",
    "joinStyle": "round",
    "layer": "86",
    "lineSize": "1",
    "lockLoc": "false",
    "margins": "4",
    "markerDrawn": "false",
    "markerFilled": "false",
    "markerLineSize": "1",
    "markerPoints": "",
    "miterLimit": "10",
    "name": "dgHeaderBottomBorder",
    "opaque": "false",
    "outerglow": "",
    "points": "",
    "polySides": "4",
    "rect": "-1,76,264,77",
    "roundEnds": "true",
    "roundRadius": "15",
    "shadowColor": "",
    "showBorder": "false",
    "showFocusBorder": "true",
    "showName": "false",
    "startAngle": "0",
    "startArrow": "false",
    "strokeGradient": "",
    "style": "rectangle",
    "textFont": "",
    "textSize": "",
    "textStyle": "",
    "threeD": "true",
    "topColor": "",
    "traversalOn": "false",
    "unicodeLabel": "",
    "unicodeText": "",
    "unicodeToolTip": "",
    "visible": "true"
  },
  "uuid": "25203D4E-F958-4471-8F3F-8EDD09C211B0"
}